har_toolkit/__init__.py
har_toolkit/parser.py
har_toolkit/utils.py
har_toolkit/har_browser/harbrowser.py
har_toolkit/har_objects/__init__.py
har_toolkit/har_objects/bases.py
har_toolkit/har_objects/browser.py
har_toolkit/har_objects/cache.py
har_toolkit/har_objects/cache_state.py
har_toolkit/har_objects/content.py
har_toolkit/har_objects/cookie.py
har_toolkit/har_objects/creator.py
har_toolkit/har_objects/entry.py
har_toolkit/har_objects/exceptions.py
har_toolkit/har_objects/header.py
har_toolkit/har_objects/page.py
har_toolkit/har_objects/page_timings.py
har_toolkit/har_objects/params.py
har_toolkit/har_objects/post_data.py
har_toolkit/har_objects/query_string.py
har_toolkit/har_objects/request.py
har_toolkit/har_objects/response.py
har_toolkit/har_objects/timings.py
har_toolkit/media/image.py
har_toolkit-0.3.0.dist-info/LICENSE
har_toolkit-0.3.0.dist-info/METADATA
har_toolkit-0.3.0.dist-info/WHEEL
har_toolkit-0.3.0.dist-info/top_level.txt
har_toolkit-0.3.0.dist-info/RECORD
