Metadata-Version: 2.1
Name: har-toolkit
Version: 0.3.0
Summary: A module to work with HAR (HTTP Archive) files.
Author-email: Mason Weaver <mason@swingproxy.com>
License: GNU General Public License v3 (GPLv3)
Project-URL: Homepage, https://github.com/Otach/Har-Toolkit.git
Classifier: Development Status :: 3 - Alpha
Classifier: Programming Language :: Python :: 3
Classifier: License :: OSI Approved :: GNU General Public License v3 (GPLv3)
Classifier: Operating System :: OS Independent
Requires-Python: >=3.6
License-File: LICENSE
